MANIFEST.in
setup.py
bin/embellish
embellish/__init__.py
embellish/_version.py
embellish/engine.py
embellish/server.py
embellish.egg-info/PKG-INFO
embellish.egg-info/SOURCES.txt
embellish.egg-info/dependency_links.txt
embellish.egg-info/requires.txt
embellish.egg-info/top_level.txt
embellish/defaults/default.haml