Metadata-Version: 1.0
Name: embellish
Version: 0.9.2
Summary: static site generator
Home-page: http://github.com/boscoh/embellish
Author: Bosco Ho
Author-email: boscoh@gmail.com
License: BSD
Platform: UNKNOWN
